ansys/optislang/__init__.py
ansys/optislang/core/__init__.py
ansys/optislang/core/application.py
ansys/optislang/core/communication_channels.py
ansys/optislang/core/encoding.py
ansys/optislang/core/errors.py
ansys/optislang/core/io.py
ansys/optislang/core/json_utils.py
ansys/optislang/core/logging.py
ansys/optislang/core/managers.py
ansys/optislang/core/node_types.py
ansys/optislang/core/nodes.py
ansys/optislang/core/optislang.py
ansys/optislang/core/osl_process.py
ansys/optislang/core/osl_server.py
ansys/optislang/core/placeholder_types.py
ansys/optislang/core/project.py
ansys/optislang/core/project_parametric.py
ansys/optislang/core/slot_types.py
ansys/optislang/core/utils.py
ansys/optislang/core/examples/__init__.py
ansys/optislang/core/examples/downloads.py
ansys/optislang/core/examples/examples.py
ansys/optislang/core/examples/00_run_script/etk_abaqus/files/oscillator.inp
ansys/optislang/core/examples/00_run_script/etk_abaqus/files/oscillator.odb
ansys/optislang/core/examples/00_run_script/etk_abaqus/scripts/etk_abaqus.py
ansys/optislang/core/examples/00_run_script/files/calculator.opf
ansys/optislang/core/examples/00_run_script/files/calculator_with_params.opf
ansys/optislang/core/examples/00_run_script/files/connect_nodes.opf
ansys/optislang/core/examples/00_run_script/files/nested_systems.opf
ansys/optislang/core/examples/00_run_script/files/omdb_files.opf
ansys/optislang/core/examples/00_run_script/files/ten_bar_truss.opf
ansys/optislang/core/examples/00_run_script/oscillator/files/oscillator.bat
ansys/optislang/core/examples/00_run_script/oscillator/files/oscillator.py
ansys/optislang/core/examples/00_run_script/oscillator/files/oscillator.s
ansys/optislang/core/examples/00_run_script/oscillator/files/oscillator.sh
ansys/optislang/core/examples/00_run_script/oscillator/files/oscillator_reference.txt
ansys/optislang/core/examples/00_run_script/oscillator/files/oscillator_signal.txt
ansys_optislang_core-1.4.1.dist-info/licenses/LICENSE
ansys_optislang_core-1.4.1.dist-info/WHEEL
ansys_optislang_core-1.4.1.dist-info/METADATA
ansys_optislang_core-1.4.1.dist-info/RECORD
