Metadata-Version: 2.4
Name: ansys-optislang-core
Version: 1.4.1
Summary: A Python wrapper for Ansys optiSLang application.
Author-email: "ANSYS, Inc." <pyansys.core@ansys.com>
Maintainer-email: "ANSYS, Inc." <pyansys.core@ansys.com>
Requires-Python: >=3.9,<4
Classifier: Development Status :: 4 - Beta
Classifier: Intended Audience :: Science/Research
Classifier: License :: OSI Approved :: MIT License
Classifier: Operating System :: OS Independent
Classifier: Programming Language :: Python :: 3
Classifier: Programming Language :: Python :: 3.9
Classifier: Programming Language :: Python :: 3.10
Classifier: Programming Language :: Python :: 3.11
Classifier: Programming Language :: Python :: 3.12
Classifier: Programming Language :: Python :: 3.13
Classifier: Topic :: Scientific/Engineering
License-File: LICENSE
Requires-Dist: psutil>=5.9
Requires-Dist: Deprecated>=1.2.14
Requires-Dist: pywin32>=304; sys_platform == 'win32'
Requires-Dist: build>=0.8.0 ; extra == "build"
Requires-Dist: twine>=4.0.1 ; extra == "build"
Requires-Dist: ansys-sphinx-theme==1.6.4 ; extra == "doc"
Requires-Dist: matplotlib==3.10.1 ; extra == "doc"
Requires-Dist: numpydoc==1.9.0 ; extra == "doc"
Requires-Dist: pypandoc==1.16.2 ; extra == "doc"
Requires-Dist: quarto-cli==1.8.25 ; extra == "doc"
Requires-Dist: Sphinx==8.2.3 ; extra == "doc"
Requires-Dist: sphinx-copybutton==0.5.2 ; extra == "doc"
Requires-Dist: sphinx-gallery==0.19.0 ; extra == "doc"
Requires-Dist: pytest==8.4.2 ; extra == "tests"
Requires-Dist: pytest-cov==7.0.0 ; extra == "tests"
Requires-Dist: matplotlib>=3.5.3 ; extra == "tests"
Requires-Dist: mypy==1.19.0 ; extra == "typing"
Requires-Dist: types-Deprecated ; extra == "typing"
Requires-Dist: types-psutil ; extra == "typing"
Project-URL: Documentation, https://optislang.docs.pyansys.com
Project-URL: Homepage, https://optislang.docs.pyansys.com
Project-URL: Source, https://github.com/ansys/pyoptislang
Project-URL: Tracker, https://github.com/ansys/pyoptislang/issues
Provides-Extra: build
Provides-Extra: doc
Provides-Extra: tests
Provides-Extra: typing
